{
  "entity": true,
  "layouts": false,
  "tab": true,
  "acl": true,
  "aclActionList": [
    "create",
    "read",
    "edit",
    "delete"
  ],
  "customizable": true,
  "importable": false,
  "notifications": false,
  "stream": false,
  "streamDisabled": true,
  "disabled": false,
  "type": "Base",
  "module": "Import",
  "object": true,
  "hasAssignedUser": false,
  "hasTeam": false,
  "hasOwner": false,
  "hideFieldTypeFilters": true,
  "autoDeleteAfterDays": 21,
  "clearDeletedAfterDays": 35,
  "disableActionHistory": true,
  "selectionDisabled": true
}